neuronpedia_autointerp_client/__init__.py
neuronpedia_autointerp_client/api_client.py
neuronpedia_autointerp_client/api_response.py
neuronpedia_autointerp_client/configuration.py
neuronpedia_autointerp_client/exceptions.py
neuronpedia_autointerp_client/py.typed
neuronpedia_autointerp_client/rest.py
neuronpedia_autointerp_client/api/__init__.py
neuronpedia_autointerp_client/api/default_api.py
neuronpedia_autointerp_client/models/__init__.py
neuronpedia_autointerp_client/models/explain_default_post200_response.py
neuronpedia_autointerp_client/models/explain_default_post_request.py
neuronpedia_autointerp_client/models/np_activation.py
neuronpedia_autointerp_client/models/np_score_fuzz_detection_type.py
neuronpedia_autointerp_client/models/score_embedding_post200_response.py
neuronpedia_autointerp_client/models/score_embedding_post200_response_breakdown_inner.py
neuronpedia_autointerp_client/models/score_embedding_post_request.py
neuronpedia_autointerp_client/models/score_fuzz_detection_post200_response.py
neuronpedia_autointerp_client/models/score_fuzz_detection_post200_response_breakdown_inner.py
neuronpedia_autointerp_client/models/score_fuzz_detection_post_request.py
neuronpedia_autointerp_client-1.0.0.dist-info/METADATA
neuronpedia_autointerp_client-1.0.0.dist-info/WHEEL
neuronpedia_autointerp_client-1.0.0.dist-info/top_level.txt
neuronpedia_autointerp_client-1.0.0.dist-info/RECORD
