Metadata-Version: 2.2
Name: neuronpedia-autointerp-client
Version: 1.0.0
Summary: Neuronpedia - AutoInterp Server
Home-page: 
Author: OpenAPI Generator community
Author-email: johnny@neuronpedia.org
License: MIT
Keywords: OpenAPI,OpenAPI-Generator,Neuronpedia - AutoInterp Server
Requires-Dist: urllib3<3.0.0,>=1.25.3
Requires-Dist: python-dateutil>=2.8.2
Requires-Dist: pydantic>=2
Requires-Dist: typing-extensions>=4.7.1
Dynamic: author
Dynamic: author-email
Dynamic: description
Dynamic: description-content-type
Dynamic: keywords
Dynamic: license
Dynamic: requires-dist
Dynamic: summary
